rptar.py
rptar-0.1.2.dist-info/METADATA
rptar-0.1.2.dist-info/WHEEL
rptar-0.1.2.dist-info/entry_points.txt
rptar-0.1.2.dist-info/licenses/LICENSE
rptar-0.1.2.dist-info/RECORD
