Metadata-Version: 2.4
Name: rptar
Version: 0.1.2
Summary: A lightweight command-line program for creating reproducible/deterministic tar archives.
Project-URL: Documentation, https://github.com/drivendataorg/repro-tarfile#readme
Project-URL: Issues, https://github.com/drivendataorg/repro-tarfile/issues
Project-URL: Source, https://github.com/drivendataorg/repro-tarfile/tree/main/cli
Author-email: DrivenData <info@drivendata.org>
License: MIT License
License-File: LICENSE
Keywords: cli,deterministic,reproducible,tar,tarfile
Classifier: Intended Audience :: Developers
Classifier: Intended Audience :: Science/Research
Classifier: License :: OSI Approved :: MIT License
Classifier: Operating System :: OS Independent
Classifier: Programming Language :: Python
Classifier: Programming Language :: Python :: 3.8
Classifier: Programming Language :: Python :: 3.9
Classifier: Programming Language :: Python :: 3.10
Classifier: Programming Language :: Python :: 3.11
Classifier: Programming Language :: Python :: 3.12
Classifier: Programming Language :: Python :: 3.13
Classifier: Topic :: System :: Archiving
Classifier: Topic :: System :: Archiving :: Compression
Classifier: Topic :: System :: Archiving :: Packaging
Requires-Python: >=3.8
Requires-Dist: repro-tarfile
Requires-Dist: typer>=0.9.0
Requires-Dist: typing-extensions>=3.9; python_version < '3.9'
